pfacbuilder/__init__.py
pfacbuilder-1.0.0.dist-info/METADATA
pfacbuilder-1.0.0.dist-info/WHEEL
pfacbuilder-1.0.0.dist-info/top_level.txt
pfacbuilder-1.0.0.dist-info/RECORD
